fastmcp_ironbook/__init__.py
fastmcp_ironbook/agent.py
fastmcp_ironbook/decorator.py
fastmcp_ironbook/middleware.py
fastmcp_ironbook/policy.py
fastmcp_ironbook-0.1.1.dist-info/METADATA
fastmcp_ironbook-0.1.1.dist-info/WHEEL
fastmcp_ironbook-0.1.1.dist-info/licenses/LICENSE
fastmcp_ironbook-0.1.1.dist-info/RECORD
