Metadata-Version: 2.4
Name: fastmcp-ironbook
Version: 0.1.1
Summary: Iron Book agent-based security integration for FastMCP servers
Project-URL: Homepage, https://github.com/identitymachines/fastmcp-ironbook
Project-URL: Documentation, https://github.com/identitymachines/fastmcp-ironbook#readme
Project-URL: Repository, https://github.com/identitymachines/fastmcp-ironbook
Project-URL: Issues, https://github.com/identitymachines/fastmcp-ironbook/issues
Author-email: Identity Machines <devops@identitymachines.com>
License: MIT
License-File: LICENSE
Keywords: authorization,fastmcp,ironbook,mcp,policy,security
Classifier: Development Status :: 3 - Alpha
Classifier: Intended Audience :: Developers
Classifier: License :: OSI Approved :: MIT License
Classifier: Programming Language :: Python :: 3
Classifier: Programming Language :: Python :: 3.10
Classifier: Programming Language :: Python :: 3.11
Classifier: Programming Language :: Python :: 3.12
Requires-Python: >=3.10
Requires-Dist: fastmcp>=0.2.0
Requires-Dist: ironbook-sdk>=0.3.0
